SuperimpositionModel/__init__.py
SuperimpositionModel/Models/IC.py
SuperimpositionModel/Models/ModelConfig.py
SuperimpositionModel/Models/SEIR.py
SuperimpositionModel/Models/SEIS.py
SuperimpositionModel/Models/SIR.py
SuperimpositionModel/Models/SIS.py
SuperimpositionModel/Models/__init__.py
superimposition_diffusion_model-0.0.2.dist-info/LICENSE
superimposition_diffusion_model-0.0.2.dist-info/METADATA
superimposition_diffusion_model-0.0.2.dist-info/WHEEL
superimposition_diffusion_model-0.0.2.dist-info/top_level.txt
superimposition_diffusion_model-0.0.2.dist-info/RECORD
