Metadata-Version: 2.1
Name: superimposition-diffusion-model
Version: 0.0.2
Summary: A software package for running diffusion simulations on regular and higher-order networks
Home-page: https://github.com/roozbehes/superimposition-diffusion
Author: Roozbeh Eslami
Author-email: eslamiroozbeh@yahoo.com
License: UNKNOWN
Project-URL: Bug Tracker, https://github.com/pypa/sampleproject/issues
Platform: UNKNOWN
Classifier: Programming Language :: Python :: 3
Classifier: License :: OSI Approved :: BSD License
Classifier: Operating System :: OS Independent
Requires-Python: >=3.6
License-File: LICENSE
